params_aws/__init__.py
params_aws/model.py
params_aws/params_aws.py
params_aws/params_aws_cli.py
params_aws-0.1.2.dist-info/METADATA
params_aws-0.1.2.dist-info/WHEEL
params_aws-0.1.2.dist-info/entry_points.txt
params_aws-0.1.2.dist-info/RECORD
