Metadata-Version: 2.1
Name: params-aws
Version: 0.1.2
Summary: Store and Load parameters with AWS Parameter store
Home-page: https://github.com/varokas/params-aws
Author: Varokas Panusuwan
Author-email: varokas@panusuwan.com
Requires-Python: >=3.8,<4.0
Classifier: Programming Language :: Python :: 3
Classifier: Programming Language :: Python :: 3.8
Classifier: Programming Language :: Python :: 3.9
Classifier: Programming Language :: Python :: 3.10
Classifier: Programming Language :: Python :: 3.11
Requires-Dist: boto3 (>=1.10)
Requires-Dist: cachetools (>=5.3.0,<6.0.0)
Requires-Dist: click (>=8.1.3,<9.0.0)
Requires-Dist: pydantic (>=1.0)
Project-URL: Repository, https://github.com/varokas/params-aws
